soma_integ/__init__.py
soma_integ/config.py
soma_integ/data.py
soma_integ/evaluation.py
soma_integ/methods.py
soma_integ/model.py
soma_integ/optimization.py
soma_integ/utils.py
soma_integ-0.1.9.dist-info/LICENSE
soma_integ-0.1.9.dist-info/METADATA
soma_integ-0.1.9.dist-info/WHEEL
soma_integ-0.1.9.dist-info/top_level.txt
soma_integ-0.1.9.dist-info/RECORD
